flask_taxonomies_es/__init__.py
flask_taxonomies_es/api.py
flask_taxonomies_es/cli.py
flask_taxonomies_es/config.py
flask_taxonomies_es/exceptions.py
flask_taxonomies_es/ext.py
flask_taxonomies_es/logger.py
flask_taxonomies_es/proxies.py
flask_taxonomies_es/serializer.py
flask_taxonomies_es/signals.py
flask_taxonomies_es/utils.py
flask_taxonomies_es/version.py
flask_taxonomies_es-1.3.5.dist-info/METADATA
flask_taxonomies_es-1.3.5.dist-info/WHEEL
flask_taxonomies_es-1.3.5.dist-info/entry_points.txt
flask_taxonomies_es-1.3.5.dist-info/top_level.txt
flask_taxonomies_es-1.3.5.dist-info/RECORD
