Metadata-Version: 2.1
Name: flask-taxonomies-es
Version: 1.3.5
Summary: Elasticsearch extension for Flask-Taxonomies
Home-page: https://github.com/oarepo/flask-taxonomies-es
Author: Daniel Kopecký
Author-email: Daniel.Kopecky@techlib.cz
License: MIT
Platform: any
Classifier: Environment :: Web Environment
Classifier: Intended Audience :: Developers
Classifier: License :: OSI Approved :: MIT License
Classifier: Operating System :: OS Independent
Classifier: Programming Language :: Python
Classifier: Topic :: Internet :: WWW/HTTP :: Dynamic Content
Classifier: Topic :: Software Development :: Libraries :: Python Modules
Classifier: Programming Language :: Python :: 3
Classifier: Programming Language :: Python :: 3.7
Classifier: Development Status :: 4 - Beta
Requires-Dist: flask-taxonomies
Requires-Dist: elasticsearch (<8.0.0,>=7.0.0)
Requires-Dist: elasticsearch-dsl (<8.0.0,>=7.0.0)
Requires-Dist: webargs (<6.0.0)
Requires-Dist: email-validator
Provides-Extra: docs
Requires-Dist: sphinx ; extra == 'docs'
Requires-Dist: webargs (<6.0.0) ; extra == 'docs'
Requires-Dist: oarepo[tests] (~=3.2.1) ; extra == 'docs'
Provides-Extra: postgresql
Requires-Dist: flask-taxonomies[postgresql] ; extra == 'postgresql'
Provides-Extra: sqlite
Requires-Dist: flask-taxonomies[sqlite] ; extra == 'sqlite'
Provides-Extra: tests
Requires-Dist: pytest (>=4.6.3) ; extra == 'tests'
Requires-Dist: pytest-cov ; extra == 'tests'
Requires-Dist: pytest-flask (==0.15.1) ; extra == 'tests'
Requires-Dist: oarepo[tests] (~=3.2.1) ; extra == 'tests'
Provides-Extra: tests-es7
Requires-Dist: pytest (>=4.6.3) ; extra == 'tests-es7'
Requires-Dist: pytest-cov ; extra == 'tests-es7'
Requires-Dist: pytest-flask (==0.15.1) ; extra == 'tests-es7'
Requires-Dist: oarepo[tests-es7] (~=3.2.1) ; extra == 'tests-es7'
